pcsx2_interface/__init__.py
pcsx2_interface/pcsx2_interface.cp312-win_amd64.pyd
pcsx2_interface-0.0.3.dist-info/METADATA
pcsx2_interface-0.0.3.dist-info/WHEEL
pcsx2_interface-0.0.3.dist-info/licenses/LICENSE
pcsx2_interface-0.0.3.dist-info/RECORD
